mongo_memory/__init__.py
mongo_memory/cli.py
mongo_memory/main.py
mongo_memory/mongo_connector.py
mongo_memory/response_utils.py
mongo_memory/constants/__init__.py
mongo_memory/constants/instructions.py
mongo_memory/constants/usage_guide.py
mongo_memory-0.3.2.dist-info/METADATA
mongo_memory-0.3.2.dist-info/WHEEL
mongo_memory-0.3.2.dist-info/entry_points.txt
mongo_memory-0.3.2.dist-info/licenses/LICENSE
mongo_memory-0.3.2.dist-info/RECORD
