Metadata-Version: 2.4
Name: mongo-memory
Version: 0.3.2
Summary: MCP-server that implements memory stored in MongoDB
Project-URL: Homepage, https://github.com/santahate/mcp-mongo-memory
Project-URL: Bug Tracker, https://github.com/santahate/mcp-mongo-memory/issues
Project-URL: Source Code, https://github.com/santahate/mcp-mongo-memory
Author-email: Vlad Babenko <vlad.babenko@gmail.com>
License: MIT
License-File: LICENSE
Keywords: database,graph,mcp,memory,mongodb
Classifier: Development Status :: 4 - Beta
Classifier: Intended Audience :: Developers
Classifier: License :: OSI Approved :: MIT License
Classifier: Programming Language :: Python :: 3
Classifier: Programming Language :: Python :: 3.12
Classifier: Topic :: Database
Classifier: Topic :: Scientific/Engineering :: Artificial Intelligence
Classifier: Topic :: Software Development :: Libraries
Requires-Python: >=3.12
Requires-Dist: mcp[cli]>=1.3.0
Requires-Dist: pymongo>=4.11.1
